[
  {
    "class":"firrtl.EmitCircuitAnnotation",
    "emitter":"firrtl.VerilogEmitter"
  },
  {
    "class":"firrtl.transforms.BlackBoxTargetDirAnno",
    "targetDir":"."
  },
  {
    "class":"firrtl.transforms.CombinationalPath",
    "sink":"~SimpleModule|SimpleModule>io_current_mask_index_0",
    "sources":[
      "~SimpleModule|SimpleModule>io_current_mask_0"
    ]
  },
  {
    "class":"firrtl.transforms.CombinationalPath",
    "sink":"~SimpleModule|SimpleModule>io_current_mask_index_3",
    "sources":[
      "~SimpleModule|SimpleModule>io_current_mask_3"
    ]
  },
  {
    "class":"firrtl.transforms.CombinationalPath",
    "sink":"~SimpleModule|SimpleModule>io_current_mask_index_2",
    "sources":[
      "~SimpleModule|SimpleModule>io_current_mask_2"
    ]
  },
  {
    "class":"firrtl.transforms.CombinationalPath",
    "sink":"~SimpleModule|SimpleModule>io_current_mask_index_1",
    "sources":[
      "~SimpleModule|SimpleModule>io_current_mask_1"
    ]
  }
]